odoo/addons/dms/README.rst
odoo/addons/dms/__init__.py
odoo/addons/dms/__manifest__.py
odoo/addons/dms/actions/file.xml
odoo/addons/dms/controllers/__init__.py
odoo/addons/dms/controllers/main.py
odoo/addons/dms/controllers/portal.py
odoo/addons/dms/demo/access_group.xml
odoo/addons/dms/demo/assets.xml
odoo/addons/dms/demo/category.xml
odoo/addons/dms/demo/directory.xml
odoo/addons/dms/demo/file.xml
odoo/addons/dms/demo/res_users.xml
odoo/addons/dms/demo/storage.xml
odoo/addons/dms/demo/tag.xml
odoo/addons/dms/demo/data/audio01.wav
odoo/addons/dms/demo/data/audio02.wav
odoo/addons/dms/demo/data/audio03.mp3
odoo/addons/dms/demo/data/audio04.mp3
odoo/addons/dms/demo/data/code01.aj
odoo/addons/dms/demo/data/code02.sh
odoo/addons/dms/demo/data/code03.c
odoo/addons/dms/demo/data/code04.cc
odoo/addons/dms/demo/data/code05.cs
odoo/addons/dms/demo/data/code06.cbl
odoo/addons/dms/demo/data/code07.coffee
odoo/addons/dms/demo/data/code08.f
odoo/addons/dms/demo/data/code09.go
odoo/addons/dms/demo/data/code10.groovy
odoo/addons/dms/demo/data/code11.java
odoo/addons/dms/demo/data/code12.sc
odoo/addons/dms/demo/data/document01.pdf
odoo/addons/dms/demo/data/document02.doc
odoo/addons/dms/demo/data/document03.odt
odoo/addons/dms/demo/data/document04.rtf
odoo/addons/dms/demo/data/image01.jpg
odoo/addons/dms/demo/data/image02.jpg
odoo/addons/dms/demo/data/image03.jpg
odoo/addons/dms/demo/data/image04.jpg
odoo/addons/dms/demo/data/mail01.eml
odoo/addons/dms/demo/data/mail02.eml
odoo/addons/dms/demo/data/markdown.md
odoo/addons/dms/demo/data/sheet01.xls
odoo/addons/dms/demo/data/sheet02.csv
odoo/addons/dms/demo/data/sheet03.ods
odoo/addons/dms/demo/data/slide01.odp
odoo/addons/dms/demo/data/slide02.ppt
odoo/addons/dms/demo/data/text.rst
odoo/addons/dms/demo/data/text.txt
odoo/addons/dms/demo/data/vector.svg
odoo/addons/dms/demo/data/video.mp4
odoo/addons/dms/i18n/da.po
odoo/addons/dms/i18n/de.po
odoo/addons/dms/i18n/dms.pot
odoo/addons/dms/i18n/es.po
odoo/addons/dms/i18n/eu.po
odoo12_addon_dms-12.0.8.0.3.dist-info/METADATA
odoo12_addon_dms-12.0.8.0.3.dist-info/WHEEL
odoo12_addon_dms-12.0.8.0.3.dist-info/top_level.txt
odoo12_addon_dms-12.0.8.0.3.dist-info/RECORD
