Metadata-Version: 2.1
Name: odoo12-addon-dms
Version: 12.0.8.0.3
Summary: Document Management System for Odoo
Home-page: https://github.com/OCA/dms
Author: MuK IT, Tecnativa, Odoo Community Association (OCA)
Author-email: support@odoo-community.org
License: LGPL-3
Platform: UNKNOWN
Classifier: Programming Language :: Python
Classifier: Framework :: Odoo
Classifier: Framework :: Odoo :: 12.0
Classifier: License :: OSI Approved :: GNU Lesser General Public License v3 (LGPLv3)
Requires-Python: >=3.5
Requires-Dist: odoo12-addon-mail-preview-base
Requires-Dist: odoo12-addon-web-drop-target
Requires-Dist: odoo12-addon-web-view-searchpanel
Requires-Dist: odoo (<12.1dev,>=12.0a)
